aixm_geo/__init__.py
aixm_geo/aixm_features.py
aixm_geo/aixm_geo.py
aixm_geo/base.py
aixm_geo/factory.py
aixm_geo/interfaces.py
aixm_geo/settings.py
aixm_geo/util.py
tests/__init__.py
tests/test_aixm_features.py
tests/test_base.py
AIXMGeo-0.0.2.dist-info/LICENCE.txt
AIXMGeo-0.0.2.dist-info/METADATA
AIXMGeo-0.0.2.dist-info/WHEEL
AIXMGeo-0.0.2.dist-info/top_level.txt
AIXMGeo-0.0.2.dist-info/RECORD
