Metadata-Version: 2.1
Name: AIXMGeo
Version: 0.0.2
Summary: A Python module which wraps KMLPlus to produce kml files from AIXM 5.1 geographical data.
Home-page: https://github.com/MHenderson1988/aixm_geo
Author: Mark Henderson
Author-email: mark.henderson1988@gmail.com
Classifier: Programming Language :: Python :: 3
Classifier: License :: OSI Approved :: MIT License
Classifier: Operating System :: OS Independent
Requires-Python: >=3.8
License-File: LICENCE.txt
